brushwood/__init__.py
brushwood/_dictloader.py
brushwood/filter/__init__.py
brushwood/filter/_abstract_base.py
brushwood/filter/children.py
brushwood/filter/conditions.py
brushwood/filter/grouping.py
brushwood/filter/parents.py
brushwood/leaf.py
brushwood/tree.py
brushwood-0.1.7.dist-info/WHEEL
brushwood-0.1.7.dist-info/METADATA
brushwood-0.1.7.dist-info/RECORD
