Metadata-Version: 2.1
Name: brushwood
Version: 0.1.7
Summary: Interleaved object structures to filterable and iteratable tree structure
License: LGPL-3.0-or-later
Author: 138
Requires-Python: >=3.8,<4.0
Classifier: License :: OSI Approved :: GNU Lesser General Public License v3 or later (LGPLv3+)
Classifier: Programming Language :: Python :: 3
Classifier: Programming Language :: Python :: 3.10
Classifier: Programming Language :: Python :: 3.8
Classifier: Programming Language :: Python :: 3.9
